{
  "households": {
    "house_cohen_001": {
      "shared_lists": {
        "list_001": {
          "id": "list_001",
          "name": "קניות שבועיות",
          "type": "supermarket",
          "status": "completed",
          "created_by": "user_yogev_001",
          "created_date": "2025-10-03T09:00:00.000Z",
          "updated_date": "2025-10-03T14:35:00.000Z",
          "is_shared": true,
          "is_private": false,
          "budget": 300.0,
          "items": [
            {
              "id": "item_001",
              "name": "חלב 3%",
              "type": "product",
              "isChecked": true,
              "category": "מוצרי חלב",
              "productData": {
                "quantity": 2,
                "unitPrice": 7.9,
                "unit": "ליטר"
              },
              "checked_by": "user_yogev_001",
              "checked_at": "2025-10-03T14:10:00.000Z"
            },
            {
              "id": "item_002",
              "name": "לחם פרוס",
              "type": "product",
              "isChecked": true,
              "category": "לחם ומאפים",
              "productData": {
                "quantity": 1,
                "unitPrice": 12.0,
                "unit": "יח'"
              },
              "checked_by": "user_yogev_001",
              "checked_at": "2025-10-03T14:12:00.000Z"
            },
            {
              "id": "item_003",
              "name": "ביצים L",
              "type": "product",
              "isChecked": true,
              "category": "ביצים",
              "productData": {
                "quantity": 1,
                "unitPrice": 28.0,
                "unit": "תבנית 30"
              },
              "checked_by": "user_yogev_001",
              "checked_at": "2025-10-03T14:15:00.000Z"
            },
            {
              "id": "item_004",
              "name": "גבינה צהובה",
              "type": "product",
              "isChecked": true,
              "category": "מוצרי חלב",
              "productData": {
                "quantity": 1,
                "unitPrice": 22.0,
                "unit": "200 גרם"
              },
              "checked_by": "user_yogev_001",
              "checked_at": "2025-10-03T14:18:00.000Z"
            },
            {
              "id": "item_005",
              "name": "יוגורט",
              "type": "product",
              "isChecked": true,
              "category": "מוצרי חלב",
              "productData": {
                "quantity": 4,
                "unitPrice": 5.5,
                "unit": "יח'"
              },
              "checked_by": "user_yogev_001",
              "checked_at": "2025-10-03T14:20:00.000Z"
            },
            {
              "id": "item_006",
              "name": "עגבניות",
              "type": "product",
              "isChecked": true,
              "category": "ירקות",
              "productData": {
                "quantity": 1,
                "unitPrice": 8.9,
                "unit": "ק\"ג"
              },
              "checked_by": "user_yogev_001",
              "checked_at": "2025-10-03T14:22:00.000Z"
            },
            {
              "id": "item_007",
              "name": "קפה נמס",
              "type": "product",
              "isChecked": false,
              "category": "משקאות חמים",
              "productData": {
                "quantity": 1,
                "unitPrice": 35.0,
                "unit": "200 גרם"
              },
              "notes": "לא היה במלאי"
            }
          ],
          "active_shoppers": [],
          "shared_users": {},
          "format": "shared"
        },
        "list_002": {
          "id": "list_002",
          "name": "בית מרקחת",
          "type": "pharmacy",
          "status": "completed",
          "created_by": "user_yogev_001",
          "created_date": "2025-10-10T08:30:00.000Z",
          "updated_date": "2025-10-10T10:15:00.000Z",
          "is_shared": true,
          "is_private": false,
          "items": [
            {
              "id": "item_010",
              "name": "אקמול",
              "type": "product",
              "isChecked": true,
              "category": "תרופות",
              "productData": {
                "quantity": 1,
                "unitPrice": 25.0,
                "unit": "חבילה"
              }
            },
            {
              "id": "item_011",
              "name": "ויטמין C",
              "type": "product",
              "isChecked": true,
              "category": "ויטמינים",
              "productData": {
                "quantity": 1,
                "unitPrice": 45.0,
                "unit": "חבילה"
              }
            },
            {
              "id": "item_012",
              "name": "משחת שיניים",
              "type": "product",
              "isChecked": true,
              "category": "היגיינה",
              "productData": {
                "quantity": 2,
                "unitPrice": 18.0,
                "unit": "יח'"
              }
            }
          ],
          "format": "shared"
        },
        "list_active_001": {
          "id": "list_active_001",
          "name": "קניות השבוע",
          "type": "supermarket",
          "status": "active",
          "created_by": "user_yogev_001",
          "created_date": "2025-12-28T09:00:00.000Z",
          "updated_date": "2025-12-28T09:30:00.000Z",
          "is_shared": true,
          "is_private": false,
          "budget": 400.0,
          "items": [
            {
              "id": "item_100",
              "name": "חלב 3%",
              "type": "product",
              "isChecked": false,
              "category": "מוצרי חלב",
              "productData": {
                "quantity": 3,
                "unitPrice": 7.9,
                "unit": "ליטר"
              }
            },
            {
              "id": "item_101",
              "name": "גבינה לבנה",
              "type": "product",
              "isChecked": false,
              "category": "מוצרי חלב",
              "productData": {
                "quantity": 2,
                "unitPrice": 8.5,
                "unit": "גביע"
              }
            },
            {
              "id": "item_102",
              "name": "לחם",
              "type": "product",
              "isChecked": false,
              "category": "לחם ומאפים",
              "productData": {
                "quantity": 2,
                "unitPrice": 12.0,
                "unit": "יח'"
              }
            },
            {
              "id": "item_103",
              "name": "עוף שלם",
              "type": "product",
              "isChecked": false,
              "category": "בשר ועוף",
              "productData": {
                "quantity": 1,
                "unitPrice": 45.0,
                "unit": "ק\"ג"
              }
            },
            {
              "id": "item_104",
              "name": "ירקות לסלט",
              "type": "product",
              "isChecked": false,
              "category": "ירקות",
              "productData": {
                "quantity": 1,
                "unitPrice": 30.0,
                "unit": "ערכה"
              }
            }
          ],
          "active_shoppers": [],
          "format": "shared"
        }
      }
    }
  },
  "groups": {
    "grp_birthday_001": {
      "lists": {
        "list_birthday_001": {
          "id": "list_birthday_001",
          "name": "מי מביא מה - יום הולדת תומר",
          "type": "event",
          "status": "active",
          "created_by": "user_yogev_001",
          "created_date": "2025-12-05T12:00:00.000Z",
          "updated_date": "2025-12-18T16:00:00.000Z",
          "is_shared": true,
          "is_private": false,
          "group_id": "grp_birthday_001",
          "event_date": "2025-12-20T14:00:00.000Z",
          "items": [
            {
              "id": "wb_001",
              "name": "עוגת יום הולדת",
              "type": "task",
              "isChecked": true,
              "category": "אוכל",
              "taskData": {
                "itemType": "whoBrings",
                "neededCount": 1,
                "volunteers": [
                  {
                    "userId": "user_dani_001",
                    "displayName": "דני לוי",
                    "volunteeredAt": "2025-12-15T14:30:00.000Z"
                  }
                ]
              },
              "notes": "עוגת שוקולד עם 8 נרות"
            },
            {
              "id": "wb_002",
              "name": "פיצה",
              "type": "task",
              "isChecked": false,
              "category": "אוכל",
              "taskData": {
                "itemType": "whoBrings",
                "neededCount": 2,
                "volunteers": [
                  {
                    "userId": "user_yogev_001",
                    "displayName": "יוגב כהן",
                    "volunteeredAt": "2025-12-06T10:00:00.000Z"
                  }
                ]
              },
              "notes": "צריך עוד מישהו!"
            },
            {
              "id": "wb_003",
              "name": "משקאות קלים",
              "type": "task",
              "isChecked": true,
              "category": "שתייה",
              "taskData": {
                "itemType": "whoBrings",
                "neededCount": 3,
                "volunteers": [
                  {
                    "userId": "user_sara_001",
                    "displayName": "שרה כהן",
                    "volunteeredAt": "2025-12-06T11:00:00.000Z",
                    "quantity": 2
                  },
                  {
                    "userId": "user_dani_001",
                    "displayName": "דני לוי",
                    "volunteeredAt": "2025-12-07T09:00:00.000Z",
                    "quantity": 1
                  }
                ]
              }
            },
            {
              "id": "wb_004",
              "name": "סלטים",
              "type": "task",
              "isChecked": false,
              "category": "אוכל",
              "taskData": {
                "itemType": "whoBrings",
                "neededCount": 2,
                "volunteers": []
              },
              "notes": "אף אחד לא התנדב עדיין!"
            },
            {
              "id": "wb_005",
              "name": "קישוטים ובלונים",
              "type": "task",
              "isChecked": true,
              "category": "קישוטים",
              "taskData": {
                "itemType": "whoBrings",
                "neededCount": 1,
                "volunteers": [
                  {
                    "userId": "user_yogev_001",
                    "displayName": "יוגב כהן",
                    "volunteeredAt": "2025-12-05T13:00:00.000Z"
                  }
                ]
              }
            },
            {
              "id": "wb_006",
              "name": "חטיפים ונשנושים",
              "type": "task",
              "isChecked": false,
              "category": "אוכל",
              "taskData": {
                "itemType": "whoBrings",
                "neededCount": 2,
                "volunteers": [
                  {
                    "userId": "user_sara_001",
                    "displayName": "שרה כהן",
                    "volunteeredAt": "2025-12-10T14:00:00.000Z"
                  }
                ]
              }
            },
            {
              "id": "wb_007",
              "name": "גלידה",
              "type": "task",
              "isChecked": false,
              "category": "קינוחים",
              "taskData": {
                "itemType": "whoBrings",
                "neededCount": 2,
                "volunteers": [
                  {
                    "userId": "user_yogev_001",
                    "displayName": "יוגב כהן",
                    "volunteeredAt": "2025-12-08T10:00:00.000Z"
                  }
                ],
                "cancelledVolunteers": [
                  {
                    "userId": "user_dani_001",
                    "displayName": "דני לוי",
                    "volunteeredAt": "2025-12-07T15:00:00.000Z",
                    "cancelledAt": "2025-12-15T09:00:00.000Z",
                    "cancelReason": "לא אוכל להגיע בזמן, סליחה"
                  }
                ]
              },
              "notes": "דני ביטל - צריך מישהו אחר!"
            },
            {
              "id": "wb_008",
              "name": "פירות חתוכים",
              "type": "task",
              "isChecked": false,
              "category": "אוכל",
              "taskData": {
                "itemType": "whoBrings",
                "neededCount": 1,
                "volunteers": [],
                "cancelledVolunteers": [
                  {
                    "userId": "user_sara_001",
                    "displayName": "שרה כהן",
                    "volunteeredAt": "2025-12-06T16:00:00.000Z",
                    "cancelledAt": "2025-12-18T11:00:00.000Z",
                    "cancelReason": "לא מספיקה להכין, יש מישהו אחר?"
                  }
                ]
              },
              "notes": "שרה ביטלה - אין מתנדבים!"
            }
          ],
          "format": "who_brings"
        },
        "list_birthday_votes": {
          "id": "list_birthday_votes",
          "name": "הצבעות - יום הולדת תומר",
          "type": "event",
          "status": "active",
          "created_by": "user_yogev_001",
          "created_date": "2025-12-08T09:00:00.000Z",
          "updated_date": "2025-12-15T20:00:00.000Z",
          "is_shared": true,
          "is_private": false,
          "group_id": "grp_birthday_001",
          "items": [
            {
              "id": "vote_001",
              "name": "להזמין DJ?",
              "type": "task",
              "isChecked": false,
              "taskData": {
                "itemType": "voting",
                "isAnonymous": false,
                "votingEndDate": "2025-12-12T18:00:00.000Z",
                "votesFor": [
                  { "userId": "user_yogev_001", "displayName": "יוגב כהן", "votedAt": "2025-12-08T09:05:00.000Z" },
                  { "userId": "user_sara_001", "displayName": "שרה כהן", "votedAt": "2025-12-08T10:00:00.000Z" }
                ],
                "votesAgainst": [
                  { "userId": "user_dani_001", "displayName": "דני לוי", "votedAt": "2025-12-08T14:00:00.000Z" }
                ],
                "votesAbstain": []
              },
              "notes": "DJ לילדים, כ-300 ש\"ח לשעה"
            },
            {
              "id": "vote_002",
              "name": "להזמין ליצנים?",
              "type": "task",
              "isChecked": false,
              "taskData": {
                "itemType": "voting",
                "isAnonymous": false,
                "votingEndDate": "2025-12-13T18:00:00.000Z",
                "votesFor": [
                  { "userId": "user_sara_001", "displayName": "שרה כהן", "votedAt": "2025-12-09T11:00:00.000Z" }
                ],
                "votesAgainst": [
                  { "userId": "user_yogev_001", "displayName": "יוגב כהן", "votedAt": "2025-12-09T10:05:00.000Z" }
                ],
                "votesAbstain": [
                  { "userId": "user_dani_001", "displayName": "דני לוי", "votedAt": "2025-12-09T15:00:00.000Z" }
                ]
              },
              "notes": "תיקו - יוגב מחליט"
            },
            {
              "id": "vote_003",
              "name": "איפה לעשות את המסיבה?",
              "type": "task",
              "isChecked": false,
              "taskData": {
                "itemType": "voting",
                "isAnonymous": false,
                "votingEndDate": "2025-12-18T18:00:00.000Z",
                "options": [
                  { "id": "opt_1", "text": "בבית" },
                  { "id": "opt_2", "text": "בפארק" },
                  { "id": "opt_3", "text": "במסעדה" },
                  { "id": "opt_4", "text": "באולם משחקים" }
                ],
                "votesFor": [
                  { "userId": "user_yogev_001", "displayName": "יוגב כהן", "votedAt": "2025-12-10T09:05:00.000Z", "option": "opt_1" },
                  { "userId": "user_sara_001", "displayName": "שרה כהן", "votedAt": "2025-12-10T12:00:00.000Z", "option": "opt_4" }
                ],
                "votesAgainst": [],
                "votesAbstain": []
              },
              "notes": "דני עדיין לא הצביע"
            },
            {
              "id": "vote_004",
              "name": "באיזו שעה להתחיל?",
              "type": "task",
              "isChecked": false,
              "taskData": {
                "itemType": "voting",
                "isAnonymous": false,
                "votingEndDate": "2025-12-19T18:00:00.000Z",
                "options": [
                  { "id": "time_1", "text": "14:00" },
                  { "id": "time_2", "text": "16:00" },
                  { "id": "time_3", "text": "17:00" }
                ],
                "votesFor": [
                  { "userId": "user_yogev_001", "displayName": "יוגב כהן", "votedAt": "2025-12-11T08:30:00.000Z", "option": "time_2" },
                  { "userId": "user_sara_001", "displayName": "שרה כהן", "votedAt": "2025-12-11T09:00:00.000Z", "option": "time_2" },
                  { "userId": "user_dani_001", "displayName": "דני לוי", "votedAt": "2025-12-11T18:00:00.000Z", "option": "time_3" }
                ],
                "votesAgainst": [],
                "votesAbstain": []
              }
            }
          ],
          "format": "voting"
        }
      }
    }
  }
}
