{
  "templateName": "拽转 砖注转",
  "description": "爪专 住 砖注",
  "icon": "",
  "items": [
    {
      "source": "bakery",
      "searchTerm": "",
      "quantity": 2,
      "unit": "'",
      "fallbackName": ""
    },
    {
      "source": "supermarket",
      "searchTerm": " 3",
      "quantity": 2,
      "unit": "专",
      "fallbackName": " 3%"
    },
    {
      "source": "supermarket",
      "searchTerm": "爪",
      "quantity": 12,
      "unit": "'",
      "fallbackName": "爪"
    },
    {
      "source": "supermarket",
      "searchTerm": " 爪",
      "quantity": 0.5,
      "unit": "拽\"",
      "fallbackName": " 爪"
    },
    {
      "source": "supermarket",
      "searchTerm": "",
      "quantity": 1,
      "unit": "'",
      "fallbackName": ""
    },
    {
      "source": "greengrocer",
      "searchTerm": "注",
      "quantity": 1,
      "unit": "拽\"",
      "fallbackName": "注转"
    },
    {
      "source": "greengrocer",
      "searchTerm": "驻驻",
      "quantity": 4,
      "unit": "'",
      "fallbackName": "驻驻"
    },
    {
      "source": "greengrocer",
      "searchTerm": "爪",
      "quantity": 1,
      "unit": "拽\"",
      "fallbackName": "爪"
    },
    {
      "source": "greengrocer",
      "searchTerm": "转驻 注抓",
      "quantity": 1,
      "unit": "拽\"",
      "fallbackName": "转驻"
    },
    {
      "source": "greengrocer",
      "searchTerm": "",
      "quantity": 1,
      "unit": "拽\"",
      "fallbackName": "转"
    }
  ]
}
